token_difr/__init__.py
token_difr/api.py
token_difr/audit.py
token_difr/common.py
token_difr/local.py
token_difr/model_registry.py
token_difr/openrouter_api.py
token_difr/py.typed
token_difr-0.1.2.dist-info/METADATA
token_difr-0.1.2.dist-info/WHEEL
token_difr-0.1.2.dist-info/licenses/LICENSE
token_difr-0.1.2.dist-info/RECORD
