Metadata-Version: 2.4
Name: token-difr
Version: 0.1.2
Summary: Verify LLM outputs using Gumbel-Max sampling verification
Project-URL: Homepage, https://github.com/adamkarvonen/token-difr
Project-URL: Repository, https://github.com/adamkarvonen/token-difr
License-Expression: MIT
License-File: LICENSE
Keywords: gumbel-max,llm,sampling,verification,vllm
Classifier: Development Status :: 3 - Alpha
Classifier: Intended Audience :: Science/Research
Classifier: License :: OSI Approved :: MIT License
Classifier: Programming Language :: Python :: 3
Classifier: Programming Language :: Python :: 3.10
Classifier: Programming Language :: Python :: 3.11
Classifier: Programming Language :: Python :: 3.12
Classifier: Topic :: Scientific/Engineering :: Artificial Intelligence
Requires-Python: >=3.10
Requires-Dist: openai>=1.0.0
Requires-Dist: tinker
Requires-Dist: torch>=2.0.0
Requires-Dist: tqdm>=4.0.0
Requires-Dist: transformers>=4.30.0
Provides-Extra: all
Requires-Dist: vllm>=0.10.1; extra == 'all'
Provides-Extra: dev
Requires-Dist: ipykernel==6.29.0; extra == 'dev'
Requires-Dist: pytest>=7.0.0; extra == 'dev'
Requires-Dist: ruff>=0.1.0; extra == 'dev'
